{
  "id": "tinkoff-credit-cash",
  "bankName": "Тинькофф Банк",
  "bankLogoUrl": "https://www.tinkoff.ru/static/img/logo.svg",
  "bankWebsite": "https://www.tinkoff.ru/",
  "productType": "credit",
  "productName": "Кредит наличными",
  "productDescription": "Деньги на любые покупки без справок о доходах и поручителей. Нужен только паспорт.",
  "conditions": {
    "maxAmount": 30000000,
    "minTerm": 1,
    "maxTerm": 15,
    "currency": "RUB",
    "collateral": false,
    "guarantor": false,
    "insurance": false,
    "description": "Кредит без справок о доходах и поручителей. Требуется только паспорт."
  },
  "borrowerRequirements": {
    "minAge": 18,
    "maxAge": 65,
    "employmentType": "any",
    "documents": [
      "паспорт"
    ]
  },
  "features": [
    {
      "name": "Онлайн оформление",
      "description": "Кредит оформляется онлайн без посещения банка.",
      "available": true
    },
    {
      "name": "Быстрое решение",
      "description": "Решение за минуту после подачи заявки.",
      "available": true
    }
  ],
  "fees": {
    "issuance": 0,
    "maintenance": 0,
    "earlyRepayment": false,
    "description": "Нет комиссии за досрочное погашение."
  },
  "penalties": {
    "latePayment": "В случае просрочки начисляется штраф в размере 1% от суммы просроченного платежа.",
    "overLimit": "",
    "description": ""
  },
  "sourceUrl": "https://www.tinkoff.ru/loans/",
  "extractedAt": "2026-04-09T12:00:00Z",
  "lastVerified": "2026-04-09T12:00:00Z",
  "isActive": true,
  "priority": 50,
  "seoTitle": "Кредит наличными без справок | Тинькофф Банк",
  "seoDescription": "Получите кредит наличными в Тинькофф Банке без справок о доходах и поручителей. Онлайн оформление, быстрый вывод средств.",
  "seoKeywords": [
    "кредит наличными",
    "тинькофф банк",
    "без справок",
    "онлайн кредит"
  ],
  "metadata": {
    "confidence": 0.8
  }
}