{
  "id": "vtb-mortgage-Ипотека на покупку жилья в новостройке",
  "bankName": "ВТБ",
  "bankLogoUrl": "https://www.vtb.ru/static/img/logo.svg",
  "bankWebsite": "https://www.vtb.ru/",
  "productType": "mortgage",
  "productName": "Ипотека на покупку жилья в новостройке",
  "productDescription": "Покупка жилья в аккредитованных новостройках. Скидка 0,4% к процентной ставке для новых зарплатных клиентов.",
  "interestRates": [
    {
      "value": 10.1,
      "type": "fixed",
      "conditions": "Ставка по программе \"Ипотека на новых территориях\""
    }
  ],
  "conditions": {
    "minAmount": 0,
    "maxAmount": 100000000,
    "minTerm": 12,
    "maxTerm": 360,
    "currency": "RUB",
    "description": "Максимальная сумма до 100 млн ₽, срок до 30 лет. Ставка доступна при покупке новостройки из аккредитованного списка ВТБ."
  },
  "borrowerRequirements": {
    "minAge": 18,
    "documents": [
      "паспорт",
      "справка о доходах"
    ]
  },
  "sourceUrl": "https://www.vtb.ru/personal/ipoteka/",
  "extractedAt": "2026-04-11T12:00:00Z",
  "lastVerified": "2026-04-11T12:00:00Z",
  "isActive": true,
  "priority": 50
}